tabernacleorm/__init__.py
tabernacleorm/database.py
tabernacleorm/decorators.py
tabernacleorm/migrations.py
tabernacleorm/model.py
tabernacleorm/query.py
tabernacleorm/session.py
tabernacleorm/cli/__init__.py
tabernacleorm/cli/commands.py
tabernacleorm/cli/main.py
tabernacleorm/cli/shell.py
tabernacleorm/cli/visuals.py
tabernacleorm/core/__init__.py
tabernacleorm/core/config.py
tabernacleorm/core/connection.py
tabernacleorm/core/registry.py
tabernacleorm/engines/__init__.py
tabernacleorm/engines/base.py
tabernacleorm/engines/mongodb.py
tabernacleorm/engines/mysql.py
tabernacleorm/engines/postgresql.py
tabernacleorm/engines/sql_translator.py
tabernacleorm/engines/sqlite.py
tabernacleorm/fields/__init__.py
tabernacleorm/migrations/__init__.py
tabernacleorm/migrations/executor.py
tabernacleorm/migrations/generator.py
tabernacleorm/migrations/migration.py
tabernacleorm/models/__init__.py
tabernacleorm/models/hooks.py
tabernacleorm/models/model.py
tabernacleorm/query/__init__.py
tabernacleorm/query/queryset.py
tabernacleorm-2.1.6.dist-info/licenses/LICENSE
tabernacleorm-2.1.6.dist-info/METADATA
tabernacleorm-2.1.6.dist-info/WHEEL
tabernacleorm-2.1.6.dist-info/entry_points.txt
tabernacleorm-2.1.6.dist-info/top_level.txt
tabernacleorm-2.1.6.dist-info/RECORD
