Metadata-Version: 2.4
Name: tabernacleorm
Version: 2.1.6
Summary: A unified, multi-engine async ORM for Python (MongoDB, PostgreSQL, MySQL, SQLite)
Author-email: Ganilson Garcia <ganilsongarcia87@gmail.com>
License: MIT
Project-URL: Homepage, https://github.com/ganilson/tabernacleorm
Project-URL: Documentation, https://github.com/ganilson/tabernacleorm#readme
Project-URL: Repository, https://github.com/ganilson/tabernacleorm
Project-URL: Issues, https://github.com/ganilson/tabernacleorm/issues
Keywords: orm,database,async,mongodb,postgresql,mysql,sqlite,fastapi
Classifier: Development Status :: 4 - Beta
Classifier: Intended Audience :: Developers
Classifier: License :: OSI Approved :: MIT License
Classifier: Operating System :: OS Independent
Classifier: Programming Language :: Python :: 3
Classifier: Programming Language :: Python :: 3.8
Classifier: Programming Language :: Python :: 3.9
Classifier: Programming Language :: Python :: 3.10
Classifier: Programming Language :: Python :: 3.11
Classifier: Programming Language :: Python :: 3.12
Classifier: Topic :: Database
Classifier: Framework :: AsyncIO
Requires-Python: >=3.8
License-File: LICENSE
Requires-Dist: pydantic>=2.0
Provides-Extra: postgresql
Requires-Dist: asyncpg>=0.27.0; extra == "postgresql"
Provides-Extra: mysql
Requires-Dist: aiomysql>=0.1.1; extra == "mysql"
Provides-Extra: mongodb
Requires-Dist: motor>=3.1.0; extra == "mongodb"
Requires-Dist: pymongo>=4.0.0; extra == "mongodb"
Provides-Extra: all
Requires-Dist: asyncpg>=0.27.0; extra == "all"
Requires-Dist: aiomysql>=0.1.1; extra == "all"
Requires-Dist: motor>=3.1.0; extra == "all"
Requires-Dist: pymongo>=4.0.0; extra == "all"
Provides-Extra: dev
Requires-Dist: pytest>=7.0.0; extra == "dev"
Requires-Dist: pytest-asyncio>=0.21.0; extra == "dev"
Requires-Dist: black>=23.0.0; extra == "dev"
Requires-Dist: isort>=5.0.0; extra == "dev"
Requires-Dist: mypy>=1.0.0; extra == "dev"
Dynamic: license-file
